qchemy/__init__.py
qchemy/_const.py
qchemy/eleconfig/__init__.py
qchemy/eleconfig/atom.py
qchemy/termsym/__init__.py
qchemy/termsym/atom.py
qchemy-0.0.2.dist-info/METADATA
qchemy-0.0.2.dist-info/WHEEL
qchemy-0.0.2.dist-info/top_level.txt
qchemy-0.0.2.dist-info/RECORD
