Metadata-Version: 2.4
Name: QChemy
Version: 0.0.2
Requires-Python: >=3.10
Requires-Dist: numpy
